<?xml version="1.0" encoding="utf-8"?>
<!DOCTYPE hibernate-mapping PUBLIC "-//Hibernate/Hibernate Mapping DTD 3.0//EN"
"http://hibernate.sourceforge.net/hibernate-mapping-3.0.dtd">
<!-- 
    Mapping file autogenerated by MyEclipse Persistence Tools
-->
<hibernate-mapping>
    <class name="com.yuxuan.po.Sjzdfl" table="sjzdfl" catalog="crm">
        <id name="sjzdflId" type="java.lang.Integer">
            <column name="sjzdfl_id" />
            <generator class="identity"></generator>
        </id>
        <property name="isOk" type="java.lang.String" column="isOk"></property>
       
        <property name="sjzdflMc" type="java.lang.String">
            <column name="sjzdfl_mc">
                <comment>数据字典分类名称</comment>
            </column>
        </property>
        <set name="sjzdxxes" inverse="true">
            <key>
                <column name="sjzdfl_id" />
            </key>
            <one-to-many class="com.yuxuan.po.Sjzdxx" />
        </set>
    </class>
</hibernate-mapping>
